configuration/__init__.py
confluent_kafka_producers_wrapper/__init__.py
confluent_kafka_producers_wrapper/producer.py
confluent_kafka_producers_wrapper/classes/SchemaRegistrySidecar.py
confluent_kafka_producers_wrapper/classes/__init__.py
confluent_kafka_producers_wrapper/communication/RESTClient.py
confluent_kafka_producers_wrapper/communication/__init__.py
confluent_kafka_producers_wrapper/helpers/__init__.py
confluent_kafka_producers_wrapper/helpers/files_operations.py
confluent_kafka_producers_wrapper/schemas_cache/__init__.py
confluent_kafka_producers_wrapper/std_ssl_cert/__init__.py
confluent_kafka_producers_wrapper/tests/__init__.py
confluent_kafka_producers_wrapper/tests/test_store_and_remove_files.py
confluent_kafka_producers_wrapper-0.0.6.dist-info/METADATA
confluent_kafka_producers_wrapper-0.0.6.dist-info/WHEEL
confluent_kafka_producers_wrapper-0.0.6.dist-info/top_level.txt
confluent_kafka_producers_wrapper-0.0.6.dist-info/RECORD
