Metadata-Version: 2.1
Name: confluent-kafka-producers-wrapper
Version: 0.0.6
Summary: Wrapper for producing messages using the confluent-kafka package.
Home-page: https://github.com/antoniodimariano/confluent_kafka_producers_wrapper
Author: Antonio Di Mariano
Author-email: antonio.dimariano@gmail.com
License: UNKNOWN
Platform: UNKNOWN
Classifier: Programming Language :: Python :: 3
Classifier: License :: OSI Approved :: MIT License
Classifier: Operating System :: OS Independent
Requires-Python: ~=3.7
Requires-Dist: avro-python3
Requires-Dist: requests
Requires-Dist: confluent-kafka
Requires-Dist: fastavro
